onelinerizer/__init__.py
onelinerizer/__main__.py
onelinerizer/onelinerizer.py
onelinerizer/runtests.py
onelinerizer/template.py
onelinerizer-1.0.4.dist-info/METADATA
onelinerizer-1.0.4.dist-info/RECORD
onelinerizer-1.0.4.dist-info/WHEEL
onelinerizer-1.0.4.dist-info/entry_points.txt
onelinerizer-1.0.4.dist-info/top_level.txt
