Metadata-Version: 2.1
Name: onelinerizer
Version: 1.0.4
Summary: Convert any Python file into a single line of code.
Home-page: https://github.com/csvoss/onelinerizer
Author: Chelsea Voss
Author-email: csvoss@mit.edu
Maintainer: Chelsea Voss and Anders Kaseorg
Maintainer-email: onelinerizer@mit.edu
License: UNKNOWN
Platform: UNKNOWN
